ansible_compat/__init__.py
ansible_compat/_version.py
ansible_compat/compatibility.py
ansible_compat/config.py
ansible_compat/constants.py
ansible_compat/errors.py
ansible_compat/loaders.py
ansible_compat/ports.py
ansible_compat/prerun.py
ansible_compat/py.typed
ansible_compat/runtime.py
ansible_compat/schema.py
ansible_compat/types.py
ansible_compat/utils.py
ansible_compat-25.11.0.dist-info/licenses/LICENSE
ansible_compat-25.11.0.dist-info/METADATA
ansible_compat-25.11.0.dist-info/WHEEL
ansible_compat-25.11.0.dist-info/top_level.txt
ansible_compat-25.11.0.dist-info/RECORD
