Metadata-Version: 2.4
Name: ansible-compat
Version: 25.11.0
Summary: Ansible compatibility goodies
Author-email: Sorin Sbarnea <ssbarnea@redhat.com>
Maintainer-email: Sorin Sbarnea <ssbarnea@redhat.com>
License-Expression: MIT
Project-URL: changelog, https://github.com/ansible/ansible-compat/releases
Project-URL: documentation, https://ansible.readthedocs.io/projects/compat/
Project-URL: homepage, https://github.com/ansible/ansible-compat
Project-URL: repository, https://github.com/ansible/ansible-compat
Keywords: ansible
Classifier: Development Status :: 5 - Production/Stable
Classifier: Environment :: Console
Classifier: Intended Audience :: Developers
Classifier: Intended Audience :: Information Technology
Classifier: Intended Audience :: System Administrators
Classifier: Operating System :: OS Independent
Classifier: Programming Language :: Python
Classifier: Programming Language :: Python :: 3
Classifier: Programming Language :: Python :: 3.10
Classifier: Programming Language :: Python :: 3.11
Classifier: Programming Language :: Python :: 3.12
Classifier: Programming Language :: Python :: 3.13
Classifier: Programming Language :: Python :: 3.14
Classifier: Topic :: Software Development :: Bug Tracking
Classifier: Topic :: Software Development :: Quality Assurance
Classifier: Topic :: Software Development :: Testing
Classifier: Topic :: System :: Systems Administration
Classifier: Topic :: Utilities
Requires-Python: >=3.10
License-File: LICENSE
Requires-Dist: ansible-core>=2.16
Requires-Dist: jsonschema>=4.6.0
Requires-Dist: packaging>=25.0
Requires-Dist: pyyaml>=6.0.2
Requires-Dist: subprocess-tee>=0.4.1
Dynamic: license-file
